cumm/__init__.py
cumm/__version__.py
cumm/common.py
cumm/constants.py
cumm/core_cc.cp310-win_amd64.pyd
cumm/dtypes.py
cumm/tensorview.py
cumm/tensorview_bind.py
cumm/tensorview_bind_anno.pyi
cumm/conv/__init__.py
cumm/conv/algo.py
cumm/conv/bases.py
cumm/conv/input_iters.py
cumm/conv/kernel.py
cumm/conv/main.py
cumm/conv/main_real.py
cumm/conv/main_real_spconv.py
cumm/conv/params.py
cumm/conv/sparse_iters.py
cumm/conv/algospec/__init__.py
cumm/conv/algospec/all.py
cumm/conv/algospec/core.py
cumm/conv/algospec/simt.py
cumm/conv/algospec/turing.py
cumm/conv/algospec/volta.py
cumm/core_cc/__init__.pyi
cumm/core_cc/tensorview_bind.pyi
cumm/core_cc/csrc/__init__.pyi
cumm/core_cc/csrc/arrayref.pyi
cumm/csrc/__init__.py
cumm/csrc/arrayref.py
cumm/cudasim/__init__.py
cumm/cudasim/checkers.py
cumm/cudasim/debug.py
cumm/gemm/__init__.py
cumm/gemm/bases.py
cumm/gemm/codeops.py
cumm/gemm/constants.py
cumm/gemm/cutlasstest.py
cumm/gemm/gather.py
cumm/gemm/kernel.py
cumm/gemm/layout.py
cumm/gemm/layout_tensorop.py
cumm/gemm/main.py
cumm/gemm/main_profile.py
cumm/gemm/main_real.py
cumm/gemm/main_simu.py
cumm/gemm/mask.py
cumm/gemm/mask_iters.py
cumm/gemm/out_iters.py
cumm/gemm/output.py
cumm/gemm/thread_map.py
cumm/gemm/turing_iters.py
cumm/gemm/turing_my_iters.py
cumm/gemm/turing_out_iters.py
cumm/gemm/utils.py
cumm/gemm/volta_iters.py
cumm/gemm/volta_out_iters.py
cumm/gemm/algospec/__init__.py
cumm/gemm/algospec/all.py
cumm/gemm/algospec/bases.py
cumm/gemm/algospec/core.py
cumm/gemm/algospec/simt.py
cumm/gemm/algospec/turing.py
cumm/gemm/algospec/volta.py
cumm/gemm/arch/__init__.py
cumm/gemm/arch/instmma.py
cumm/gemm/arch/ldmatrix.py
cumm/gemm/arch/memory.py
cumm/gemm/arch/tensorop.py
cumm/gemm/blockmma/__init__.py
cumm/gemm/blockmma/mma.py
cumm/gemm/blockmma/mma_async.py
cumm/gemm/core/__init__.py
cumm/gemm/core/metaarray.py
cumm/gemm/frozen/__init__.py
cumm/gemm/frozen/mask_iters.py
cumm/gemm/gemmmath/__init__.py
cumm/gemm/output_op/__init__.py
cumm/gemm/output_op/apply.py
cumm_cu111-0.2.9.dist-info/LICENSE
cumm_cu111-0.2.9.dist-info/METADATA
cumm_cu111-0.2.9.dist-info/WHEEL
cumm_cu111-0.2.9.dist-info/top_level.txt
cumm_cu111-0.2.9.dist-info/RECORD
